nasdaq_data/__init__.py
nasdaq_data/nasdaq_grabber.py
nasdaq_data-0.1.1.dist-info/LICENSE.md
nasdaq_data-0.1.1.dist-info/METADATA
nasdaq_data-0.1.1.dist-info/WHEEL
nasdaq_data-0.1.1.dist-info/top_level.txt
nasdaq_data-0.1.1.dist-info/RECORD
