Metadata-Version: 2.1
Name: nasdaq_data
Version: 0.1.1
Summary: A handy tool to get nasdaq data in python
Home-page: https://github.com/Aidzillafont/nasdaq_app
Author: Aidzillafont
Author-email: aheffernan0@gmail.com
License: MIT
License-File: LICENSE.md
